{
  "updated": "2026-07-21 17:50 UTC",
  "symbols": {
    "XAU/USD": {
      "M1": {
        "bias": "WAIT",
        "conf": 34,
        "price": 4068.9,
        "rsi": 35.7,
        "utbot": "BUY",
        "utbot_fresh": "",
        "dir": "BEARISH",
        "htf": "BULLISH",
        "adx": 33.8
      },
      "M5": {
        "bias": "WAIT",
        "conf": 36,
        "price": 4068.9,
        "rsi": 40.9,
        "utbot": "SELL",
        "utbot_fresh": "",
        "dir": "BULLISH",
        "htf": "BULLISH",
        "adx": 22.0
      },
      "M15": {
        "bias": "WAIT",
        "conf": 38,
        "price": 4068.9,
        "rsi": 50.2,
        "utbot": "SELL",
        "utbot_fresh": "",
        "dir": "BULLISH",
        "htf": "BULLISH",
        "adx": 19.0
      }
    },
    "BTC/USD": {
      "M1": {
        "bias": "WAIT",
        "conf": 34,
        "price": 66338.4,
        "rsi": 44.9,
        "utbot": "BUY",
        "utbot_fresh": "",
        "dir": "BEARISH",
        "htf": "BULLISH",
        "adx": 37.0
      },
      "M5": {
        "bias": "WAIT",
        "conf": 20,
        "price": 66342.3,
        "rsi": 36.9,
        "utbot": "SELL",
        "utbot_fresh": "",
        "dir": "RANGING",
        "htf": "BULLISH",
        "adx": 22.9
      },
      "M15": {
        "bias": "WAIT",
        "conf": 36,
        "price": 66343.8,
        "rsi": 42.9,
        "utbot": "SELL",
        "utbot_fresh": "",
        "dir": "BULLISH",
        "htf": "BULLISH",
        "adx": 25.4
      }
    },
    "ETH/USD": {
      "M1": {
        "bias": "WAIT",
        "conf": 40,
        "price": 1923.0,
        "rsi": 47.1,
        "utbot": "BUY",
        "utbot_fresh": "",
        "dir": "BEARISH",
        "htf": "BULLISH",
        "adx": 24.6
      },
      "M5": {
        "bias": "WAIT",
        "conf": 34,
        "price": 1923.0,
        "rsi": 42.2,
        "utbot": "SELL",
        "utbot_fresh": "",
        "dir": "BEARISH",
        "htf": "BULLISH",
        "adx": 30.3
      },
      "M15": {
        "bias": "WAIT",
        "conf": 36,
        "price": 1922.8,
        "rsi": 40.1,
        "utbot": "SELL",
        "utbot_fresh": "",
        "dir": "BULLISH",
        "htf": "BULLISH",
        "adx": 28.4
      }
    }
  }
}